{
  "version": "param 2.0",
  "name": "parameter file",
  "color_patch": {
    "color1_lower": [
      118,
      16,
      202
    ],
    "enemy_upper": [
      235,
      122,
      56
    ],
    "color2_upper": [
      118,
      157,
      79
    ],
    "color3_lower": [
      123,
      -5,
      46
    ],
    "ball_lower": [
      32,
      215,
      214
    ],
    "our_upper": [
      72,
      53,
      217
    ],
    "ball_upper": [
      173,
      280,
      280
    ],
    "color1_upper": [
      220,
      62,
      245
    ],
    "color2_lower": [
      63,
      95,
      28
    ],
    "our_lower": [
      20,
      10,
      146
    ],
    "color3_upper": [
      251,
      95,
      157
    ],
    "enemy_lower": [
      163,
      58,
      11
    ]
  },
  "special_point": {
    "field_pos": [
      [
        176,
        107
      ],
      [
        1363,
        101
      ],
      [
        1374,
        269
      ],
      [
        1440,
        272
      ],
      [
        1449,
        553
      ],
      [
        1383,
        556
      ],
      [
        1386,
        735
      ],
      [
        154,
        748
      ],
      [
        159,
        564
      ],
      [
        90,
        563
      ],
      [
        101,
        281
      ],
      [
        167,
        278
      ]
    ],
    "penalty_pos": [
      [
        233,
        262
      ],
      [
        1309,
        259
      ],
      [
        1318,
        572
      ],
      [
        225,
        579
      ]
    ],
    "camera_project": [
      769,
      314
    ],
    "middle": [
      769,
      422
    ]
  }
}